db_hammer/__init__.py
db_hammer/base.py
db_hammer/csv.py
db_hammer/entity_util.py
db_hammer/mssql.py
db_hammer/mysql.py
db_hammer/oracle.py
db_hammer/page.py
db_hammer/postgresql.py
db_hammer/pysqlite3.py
db_hammer/sql_exception.py
db_hammer/auto/base_driver.py
db_hammer/auto/chrome_driver.py
db_hammer/auto/chrome_utils.py
db_hammer/auto/download.py
db_hammer/auto/firefox_driver.py
db_hammer/auto/user_agent.py
db_hammer/auto/util.py
db_hammer/util/ann.py
db_hammer/util/array_util.py
db_hammer/util/cmd.py
db_hammer/util/date.py
db_hammer/util/dict_util.py
db_hammer/util/file.py
db_hammer/util/hurbao_tool.py
db_hammer/util/idno_gen.py
db_hammer/util/keep.py
db_hammer/util/log.py
db_hammer/util/net.py
db_hammer/util/sim_email.py
db_hammer/util/ssh.py
db_hammer-0.0.60.dist-info/LICENSE
db_hammer-0.0.60.dist-info/METADATA
db_hammer-0.0.60.dist-info/WHEEL
db_hammer-0.0.60.dist-info/top_level.txt
db_hammer-0.0.60.dist-info/RECORD
