Metadata-Version: 2.1
Name: db-hammer
Version: 0.0.60
Summary: database tools；数据库操作
Author: hammer
Author-email: liuzhuogood@foxmail.com
License-File: LICENSE
